<?xml version="1.0" encoding="UTF-8" standalone="no"?>
<beans xmlns="http://www.springframework.org/schema/beans"
       xmlns:util="http://www.springframework.org/schema/util"
       xmlns:xsi="http://www.w3.org/2001/XMLSchema-instance"
       xsi:schemaLocation="
        http://www.springframework.org/schema/beans http://www.springframework.org/schema/beans/spring-beans.xsd
        http://www.springframework.org/schema/util http://www.springframework.org/schema/util/spring-util.xsd">

  <!-- Converters for RPC -->
  <bean id="litenWebsite.webmvc.protobufConverter"
        class="com.truward.brikar.protobuf.http.ProtobufHttpMessageConverter" />
  <bean id="litenWebsite.webmvc.jsonProtobufConverter"
        class="com.truward.brikar.protobuf.http.json.ProtobufJsonHttpMessageConverter" />
  <bean id="litenWebsite.webmvc.stringConverter"
        class="org.springframework.http.converter.StringHttpMessageConverter" />

  <bean id="litenWebsite.restOperationsFactory" class="com.truward.brikar.client.rest.RestOperationsFactory">
    <constructor-arg>
      <util:list>
        <ref bean="litenWebsite.webmvc.jsonProtobufConverter"/>
      </util:list>
    </constructor-arg>
    <property name="credentials">
      <util:list>
        <bean class="com.truward.brikar.client.rest.ServiceClientCredentials">
          <constructor-arg value="${litenWebsite.remote.userService.uri}"/>
          <constructor-arg value="${litenWebsite.remote.userService.username}"/>
          <constructor-arg value="${litenWebsite.remote.userService.password}"/>
        </bean>
      </util:list>
    </property>
  </bean>

  <bean id="litenWebsite.restOperations"
        factory-bean="litenWebsite.restOperationsFactory"
        factory-method="getRestOperations"/>

  <!-- Rest Binder -->
  <bean id="litenWebsite.restBinder" class="com.truward.brikar.client.rest.support.StandardRestServiceBinder">
    <constructor-arg ref="litenWebsite.restOperations" />
  </bean>
</beans>